{
  "type": "FeatureCollection",
  "features": [
    {
      "type": "Feature",
      "geometry": {
        "type": "Point",
        "coordinates": [
          -4.250057461667261,
          53.33224736518488
        ]
      },
      "properties": {
        "id": "LL738NY",
        "quality": 10,
        "easting": 250185,
        "northing": 384094,
        "country": "W92000004",
        "nhsRegionalHealthAuthority": "",
        "nhsHealthAuthority": "",
        "county": "",
        "district": "W06000001",
        "ward": "W05000987"
      }
    },
    {
      "type": "Feature",
      "geometry": {
        "type": "Point",
        "coordinates": [
          -4.244647251496025,
          53.335343541082835
        ]
      },
      "properties": {
        "id": "LL738PA",
        "quality": 10,
        "easting": 250556,
        "northing": 384427,
        "country": "W92000004",
        "nhsRegionalHealthAuthority": "",
        "nhsHealthAuthority": "",
        "county": "",
        "district": "W06000001",
        "ward": "W05000987"
      }
    },
    {
      "type": "Feature",
      "geometry": {
        "type": "Point",
        "coordinates": [
          -4.242103141987234,
          53.33581400187074
        ]
      },
      "properties": {
        "id": "LL738PB",
        "quality": 10,
        "easting": 250727,
        "northing": 384474,
        "country": "W92000004",
        "nhsRegionalHealthAuthority": "",
        "nhsHealthAuthority": "",
        "county": "",
        "district": "W06000001",
        "ward": "W05000987"
      }
    },
    {
      "type": "Feature",
      "geometry": {
        "type": "Point",
        "coordinates": [
          -4.241626230570392,
          53.33789105214123
        ]
      },
      "properties": {
        "id": "LL738PD",
        "quality": 10,
        "easting": 250766,
        "northing": 384704,
        "country": "W92000004",
        "nhsRegionalHealthAuthority": "",
        "nhsHealthAuthority": "",
        "county": "",
        "district": "W06000001",
        "ward": "W05000987"
      }
    },
    {
      "type": "Feature",
      "geometry": {
        "type": "Point",
        "coordinates": [
          -4.245825777826152,
          53.336616158979105
        ]
      },
      "properties": {
        "id": "LL738PE",
        "quality": 10,
        "easting": 250482,
        "northing": 384571,
        "country": "W92000004",
        "nhsRegionalHealthAuthority": "",
        "nhsHealthAuthority": "",
        "county": "",
        "district": "W06000001",
        "ward": "W05000987"
      }
    },
    {
      "type": "Feature",
      "geometry": {
        "type": "Point",
        "coordinates": [
          -4.24572462890448,
          53.33297642942955
        ]
      },
      "properties": {
        "id": "LL738PF",
        "quality": 10,
        "easting": 250476,
        "northing": 384166,
        "country": "W92000004",
        "nhsRegionalHealthAuthority": "",
        "nhsHealthAuthority": "",
        "county": "",
        "district": "W06000001",
        "ward": "W05000987"
      }
    },
    {
      "type": "Feature",
      "geometry": {
        "type": "Point",
        "coordinates": [
          -4.24276959922658,
          53.33420095221898
        ]
      },
      "properties": {
        "id": "LL738PG",
        "quality": 10,
        "easting": 250677,
        "northing": 384296,
        "country": "W92000004",
        "nhsRegionalHealthAuthority": "",
        "nhsHealthAuthority": "",
        "county": "",
        "district": "W06000001",
        "ward": "W05000987"
      }
    },
    {
      "type": "Feature",
      "geometry": {
        "type": "Point",
        "coordinates": [
          -4.2516509533070055,
          53.337117768750694
        ]
      },
      "properties": {
        "id": "LL738PH",
        "quality": 10,
        "easting": 250096,
        "northing": 384639,
        "country": "W92000004",
        "nhsRegionalHealthAuthority": "",
        "nhsHealthAuthority": "",
        "county": "",
        "district": "W06000001",
        "ward": "W05000987"
      }
    },
    {
      "type": "Feature",
      "geometry": {
        "type": "Point",
        "coordinates": [
          -4.236964473284428,
          53.336081329870424
        ]
      },
      "properties": {
        "id": "LL738PL",
        "quality": 10,
        "easting": 251070,
        "northing": 384493,
        "country": "W92000004",
        "nhsRegionalHealthAuthority": "",
        "nhsHealthAuthority": "",
        "county": "",
        "district": "W06000001",
        "ward": "W05000987"
      }
    },
    {
      "type": "Feature",
      "geometry": {
        "type": "Point",
        "coordinates": [
          -4.23307770554844,
          53.340757893362685
        ]
      },
      "properties": {
        "id": "LL738PN",
        "quality": 10,
        "easting": 251345,
        "northing": 385005,
        "country": "W92000004",
        "nhsRegionalHealthAuthority": "",
        "nhsHealthAuthority": "",
        "county": "",
        "district": "W06000001",
        "ward": "W05000987"
      }
    },
    {
      "type": "Feature",
      "geometry": {
        "type": "Point",
        "coordinates": [
          -4.244137724982611,
          53.32850146133462
        ]
      },
      "properties": {
        "id": "LL738PP",
        "quality": 10,
        "easting": 250566,
        "northing": 383665,
        "country": "W92000004",
        "nhsRegionalHealthAuthority": "",
        "nhsHealthAuthority": "",
        "county": "",
        "district": "W06000001",
        "ward": "W05000987"
      }
    },
    {
      "type": "Feature",
      "geometry": {
        "type": "Point",
        "coordinates": [
          -4.244461564086084,
          53.330950099610305
        ]
      },
      "properties": {
        "id": "LL738PW",
        "quality": 10,
        "easting": 250553,
        "northing": 383938,
        "country": "W92000004",
        "nhsRegionalHealthAuthority": "",
        "nhsHealthAuthority": "",
        "county": "",
        "district": "W06000001",
        "ward": "W05000987"
      }
    }
  ]
}