{
  "type": "FeatureCollection",
  "features": [
    {
      "type": "Feature",
      "geometry": {
        "type": "Point",
        "coordinates": [
          -0.12305617969681089,
          51.499328925072575
        ]
      },
      "properties": {
        "id": "SW1A0AA",
        "quality": 10,
        "easting": 530268,
        "northing": 179545,
        "country": "E92000001",
        "nhsRegionalHealthAuthority": "E19000003",
        "nhsHealthAuthority": "E18000007",
        "county": "",
        "district": "E09000033",
        "ward": "E05000644"
      }
    },
    {
      "type": "Feature",
      "geometry": {
        "type": "Point",
        "coordinates": [
          -0.12305617969681089,
          51.499328925072575
        ]
      },
      "properties": {
        "id": "SW1A0PW",
        "quality": 10,
        "easting": 530268,
        "northing": 179545,
        "country": "E92000001",
        "nhsRegionalHealthAuthority": "E19000003",
        "nhsHealthAuthority": "E18000007",
        "county": "",
        "district": "E09000033",
        "ward": "E05000644"
      }
    },
    {
      "type": "Feature",
      "geometry": {
        "type": "Point",
        "coordinates": [
          -0.12305617969681089,
          51.499328925072575
        ]
      },
      "properties": {
        "id": "SW1A0RS",
        "quality": 10,
        "easting": 530268,
        "northing": 179545,
        "country": "E92000001",
        "nhsRegionalHealthAuthority": "E19000003",
        "nhsHealthAuthority": "E18000007",
        "county": "",
        "district": "E09000033",
        "ward": "E05000644"
      }
    },
    {
      "type": "Feature",
      "geometry": {
        "type": "Point",
        "coordinates": [
          -0.13419911997914444,
          51.48052129148481
        ]
      },
      "properties": {
        "id": "SW1A0WZ",
        "quality": 10,
        "easting": 529548,
        "northing": 177434,
        "country": "E92000001",
        "nhsRegionalHealthAuthority": "E19000003",
        "nhsHealthAuthority": "E18000007",
        "county": "",
        "district": "E09000032",
        "ward": "E05000620"
      }
    },
    {
      "type": "Feature",
      "geometry": {
        "type": "Point",
        "coordinates": [
          -0.139982926310824,
          51.50049800531868
        ]
      },
      "properties": {
        "id": "SW1A1AA",
        "quality": 10,
        "easting": 529090,
        "northing": 179645,
        "country": "E92000001",
        "nhsRegionalHealthAuthority": "E19000003",
        "nhsHealthAuthority": "E18000007",
        "county": "",
        "district": "E09000033",
        "ward": "E05000644"
      }
    },
    {
      "type": "Feature",
      "geometry": {
        "type": "Point",
        "coordinates": [
          -0.13694828269186562,
          51.50353462399993
        ]
      },
      "properties": {
        "id": "SW1A1BA",
        "quality": 10,
        "easting": 529292,
        "northing": 179988,
        "country": "E92000001",
        "nhsRegionalHealthAuthority": "E19000003",
        "nhsHealthAuthority": "E18000007",
        "county": "",
        "district": "E09000033",
        "ward": "E05000644"
      }
    },
    {
      "type": "Feature",
      "geometry": {
        "type": "Point",
        "coordinates": [
          -0.1375468055721549,
          51.50334627324104
        ]
      },
      "properties": {
        "id": "SW1A1BB",
        "quality": 10,
        "easting": 529251,
        "northing": 179966,
        "country": "E92000001",
        "nhsRegionalHealthAuthority": "E19000003",
        "nhsHealthAuthority": "E18000007",
        "county": "",
        "district": "E09000033",
        "ward": "E05000644"
      }
    },
    {
      "type": "Feature",
      "geometry": {
        "type": "Point",
        "coordinates": [
          -0.1382030415056396,
          51.503509584903625
        ]
      },
      "properties": {
        "id": "SW1A1BD",
        "quality": 10,
        "easting": 529205,
        "northing": 179983,
        "country": "E92000001",
        "nhsRegionalHealthAuthority": "E19000003",
        "nhsHealthAuthority": "E18000007",
        "county": "",
        "district": "E09000033",
        "ward": "E05000644"
      }
    },
    {
      "type": "Feature",
      "geometry": {
        "type": "Point",
        "coordinates": [
          -0.1353676987628669,
          51.50448080671091
        ]
      },
      "properties": {
        "id": "SW1A1BG",
        "quality": 10,
        "easting": 529399,
        "northing": 180096,
        "country": "E92000001",
        "nhsRegionalHealthAuthority": "E19000003",
        "nhsHealthAuthority": "E18000007",
        "county": "",
        "district": "E09000033",
        "ward": "E05000644"
      }
    },
    {
      "type": "Feature",
      "geometry": {
        "type": "Point",
        "coordinates": [
          -0.1373128233779311,
          51.5037832415389
        ]
      },
      "properties": {
        "id": "SW1A1BH",
        "quality": 10,
        "easting": 529266,
        "northing": 180015,
        "country": "E92000001",
        "nhsRegionalHealthAuthority": "E19000003",
        "nhsHealthAuthority": "E18000007",
        "county": "",
        "district": "E09000033",
        "ward": "E05000644"
      }
    },
    {
      "type": "Feature",
      "geometry": {
        "type": "Point",
        "coordinates": [
          -0.13612236172528383,
          51.50399815810776
        ]
      },
      "properties": {
        "id": "SW1A1BJ",
        "quality": 10,
        "easting": 529348,
        "northing": 180041,
        "country": "E92000001",
        "nhsRegionalHealthAuthority": "E19000003",
        "nhsHealthAuthority": "E18000007",
        "county": "",
        "district": "E09000033",
        "ward": "E05000644"
      }
    },
    {
      "type": "Feature",
      "geometry": {
        "type": "Point",
        "coordinates": [
          -0.13612236172528383,
          51.50399815810776
        ]
      },
      "properties": {
        "id": "SW1A1BL",
        "quality": 10,
        "easting": 529348,
        "northing": 180041,
        "country": "E92000001",
        "nhsRegionalHealthAuthority": "E19000003",
        "nhsHealthAuthority": "E18000007",
        "county": "",
        "district": "E09000033",
        "ward": "E05000644"
      }
    },
    {
      "type": "Feature",
      "geometry": {
        "type": "Point",
        "coordinates": [
          -0.13612236172528383,
          51.50399815810776
        ]
      },
      "properties": {
        "id": "SW1A1BN",
        "quality": 10,
        "easting": 529348,
        "northing": 180041,
        "country": "E92000001",
        "nhsRegionalHealthAuthority": "E19000003",
        "nhsHealthAuthority": "E18000007",
        "county": "",
        "district": "E09000033",
        "ward": "E05000644"
      }
    },
    {
      "type": "Feature",
      "geometry": {
        "type": "Point",
        "coordinates": [
          -0.13726192077539914,
          51.50397129786976
        ]
      },
      "properties": {
        "id": "SW1A1BQ",
        "quality": 10,
        "easting": 529269,
        "northing": 180036,
        "country": "E92000001",
        "nhsRegionalHealthAuthority": "E19000003",
        "nhsHealthAuthority": "E18000007",
        "county": "",
        "district": "E09000033",
        "ward": "E05000644"
      }
    },
    {
      "type": "Feature",
      "geometry": {
        "type": "Point",
        "coordinates": [
          -0.13612236172528383,
          51.50399815810776
        ]
      },
      "properties": {
        "id": "SW1A1BS",
        "quality": 10,
        "easting": 529348,
        "northing": 180041,
        "country": "E92000001",
        "nhsRegionalHealthAuthority": "E19000003",
        "nhsHealthAuthority": "E18000007",
        "county": "",
        "district": "E09000033",
        "ward": "E05000644"
      }
    },
    {
      "type": "Feature",
      "geometry": {
        "type": "Point",
        "coordinates": [
          -0.13842650432947304,
          51.5036840104123
        ]
      },
      "properties": {
        "id": "SW1A1BW",
        "quality": 10,
        "easting": 529189,
        "northing": 180002,
        "country": "E92000001",
        "nhsRegionalHealthAuthority": "E19000003",
        "nhsHealthAuthority": "E18000007",
        "county": "",
        "district": "E09000033",
        "ward": "E05000644"
      }
    },
    {
      "type": "Feature",
      "geometry": {
        "type": "Point",
        "coordinates": [
          -0.1374304478332075,
          51.504432646732596
        ]
      },
      "properties": {
        "id": "SW1A1DA",
        "quality": 10,
        "easting": 529256,
        "northing": 180087,
        "country": "E92000001",
        "nhsRegionalHealthAuthority": "E19000003",
        "nhsHealthAuthority": "E18000007",
        "county": "",
        "district": "E09000033",
        "ward": "E05000644"
      }
    },
    {
      "type": "Feature",
      "geometry": {
        "type": "Point",
        "coordinates": [
          -0.13727606107855658,
          51.50433126517181
        ]
      },
      "properties": {
        "id": "SW1A1DD",
        "quality": 10,
        "easting": 529267,
        "northing": 180076,
        "country": "E92000001",
        "nhsRegionalHealthAuthority": "E19000003",
        "nhsHealthAuthority": "E18000007",
        "county": "",
        "district": "E09000033",
        "ward": "E05000644"
      }
    },
    {
      "type": "Feature",
      "geometry": {
        "type": "Point",
        "coordinates": [
          -0.13798969557712223,
          51.503793991520205
        ]
      },
      "properties": {
        "id": "SW1A1DH",
        "quality": 10,
        "easting": 529219,
        "northing": 180015,
        "country": "E92000001",
        "nhsRegionalHealthAuthority": "E19000003",
        "nhsHealthAuthority": "E18000007",
        "county": "",
        "district": "E09000033",
        "ward": "E05000644"
      }
    },
    {
      "type": "Feature",
      "geometry": {
        "type": "Point",
        "coordinates": [
          -0.13812539554446202,
          51.50435374731925
        ]
      },
      "properties": {
        "id": "SW1A1DP",
        "quality": 10,
        "easting": 529208,
        "northing": 180077,
        "country": "E92000001",
        "nhsRegionalHealthAuthority": "E19000003",
        "nhsHealthAuthority": "E18000007",
        "county": "",
        "district": "E09000033",
        "ward": "E05000644"
      }
    },
    {
      "type": "Feature",
      "geometry": {
        "type": "Point",
        "coordinates": [
          -0.13814430602274416,
          51.50459687384468
        ]
      },
      "properties": {
        "id": "SW1A1DR",
        "quality": 10,
        "easting": 529206,
        "northing": 180104,
        "country": "E92000001",
        "nhsRegionalHealthAuthority": "E19000003",
        "nhsHealthAuthority": "E18000007",
        "county": "",
        "district": "E09000033",
        "ward": "E05000644"
      }
    },
    {
      "type": "Feature",
      "geometry": {
        "type": "Point",
        "coordinates": [
          -0.13618952520011773,
          51.505177383011535
        ]
      },
      "properties": {
        "id": "SW1A1EA",
        "quality": 10,
        "easting": 529340,
        "northing": 180172,
        "country": "E92000001",
        "nhsRegionalHealthAuthority": "E19000003",
        "nhsHealthAuthority": "E18000007",
        "county": "",
        "district": "E09000033",
        "ward": "E05000644"
      }
    },
    {
      "type": "Feature",
      "geometry": {
        "type": "Point",
        "coordinates": [
          -0.1365282043869563,
          51.50535364329809
        ]
      },
      "properties": {
        "id": "SW1A1EE",
        "quality": 10,
        "easting": 529316,
        "northing": 180191,
        "country": "E92000001",
        "nhsRegionalHealthAuthority": "E19000003",
        "nhsHealthAuthority": "E18000007",
        "county": "",
        "district": "E09000033",
        "ward": "E05000644"
      }
    },
    {
      "type": "Feature",
      "geometry": {
        "type": "Point",
        "coordinates": [
          -0.1363294124948596,
          51.50492778644335
        ]
      },
      "properties": {
        "id": "SW1A1EF",
        "quality": 10,
        "easting": 529331,
        "northing": 180144,
        "country": "E92000001",
        "nhsRegionalHealthAuthority": "E19000003",
        "nhsHealthAuthority": "E18000007",
        "county": "",
        "district": "E09000033",
        "ward": "E05000644"
      }
    },
    {
      "type": "Feature",
      "geometry": {
        "type": "Point",
        "coordinates": [
          -0.13645462851668866,
          51.505037699234414
        ]
      },
      "properties": {
        "id": "SW1A1EG",
        "quality": 10,
        "easting": 529322,
        "northing": 180156,
        "country": "E92000001",
        "nhsRegionalHealthAuthority": "E19000003",
        "nhsHealthAuthority": "E18000007",
        "county": "",
        "district": "E09000033",
        "ward": "E05000644"
      }
    },
    {
      "type": "Feature",
      "geometry": {
        "type": "Point",
        "coordinates": [
          -0.13741578581266092,
          51.504792156495654
        ]
      },
      "properties": {
        "id": "SW1A1EJ",
        "quality": 10,
        "easting": 529256,
        "northing": 180127,
        "country": "E92000001",
        "nhsRegionalHealthAuthority": "E19000003",
        "nhsHealthAuthority": "E18000007",
        "county": "",
        "district": "E09000033",
        "ward": "E05000644"
      }
    },
    {
      "type": "Feature",
      "geometry": {
        "type": "Point",
        "coordinates": [
          -0.13692716344398762,
          51.505818654407605
        ]
      },
      "properties": {
        "id": "SW1A1ER",
        "quality": 10,
        "easting": 529287,
        "northing": 180242,
        "country": "E92000001",
        "nhsRegionalHealthAuthority": "E19000003",
        "nhsHealthAuthority": "E18000007",
        "county": "",
        "district": "E09000033",
        "ward": "E05000644"
      }
    },
    {
      "type": "Feature",
      "geometry": {
        "type": "Point",
        "coordinates": [
          -0.13726438382523792,
          51.506030863586275
        ]
      },
      "properties": {
        "id": "SW1A1ES",
        "quality": 10,
        "easting": 529263,
        "northing": 180265,
        "country": "E92000001",
        "nhsRegionalHealthAuthority": "E19000003",
        "nhsHealthAuthority": "E18000007",
        "county": "",
        "district": "E09000033",
        "ward": "E05000644"
      }
    },
    {
      "type": "Feature",
      "geometry": {
        "type": "Point",
        "coordinates": [
          -0.13720687921765376,
          51.50638069912769
        ]
      },
      "properties": {
        "id": "SW1A1HA",
        "quality": 10,
        "easting": 529266,
        "northing": 180304,
        "country": "E92000001",
        "nhsRegionalHealthAuthority": "E19000003",
        "nhsHealthAuthority": "E18000007",
        "county": "",
        "district": "E09000033",
        "ward": "E05000644"
      }
    },
    {
      "type": "Feature",
      "geometry": {
        "type": "Point",
        "coordinates": [
          -0.13797068062975887,
          51.506734585246726
        ]
      },
      "properties": {
        "id": "SW1A1HD",
        "quality": 10,
        "easting": 529212,
        "northing": 180342,
        "country": "E92000001",
        "nhsRegionalHealthAuthority": "E19000003",
        "nhsHealthAuthority": "E18000007",
        "county": "",
        "district": "E09000033",
        "ward": "E05000644"
      }
    },
    {
      "type": "Feature",
      "geometry": {
        "type": "Point",
        "coordinates": [
          -0.13784215791761698,
          51.506705563708955
        ]
      },
      "properties": {
        "id": "SW1A1HE",
        "quality": 10,
        "easting": 529221,
        "northing": 180339,
        "country": "E92000001",
        "nhsRegionalHealthAuthority": "E19000003",
        "nhsHealthAuthority": "E18000007",
        "county": "",
        "district": "E09000033",
        "ward": "E05000644"
      }
    },
    {
      "type": "Feature",
      "geometry": {
        "type": "Point",
        "coordinates": [
          -0.13419911997914444,
          51.48052129148481
        ]
      },
      "properties": {
        "id": "SW1A1HG",
        "quality": 10,
        "easting": 529548,
        "northing": 177434,
        "country": "E92000001",
        "nhsRegionalHealthAuthority": "E19000003",
        "nhsHealthAuthority": "E18000007",
        "county": "",
        "district": "E09000032",
        "ward": "E05000620"
      }
    },
    {
      "type": "Feature",
      "geometry": {
        "type": "Point",
        "coordinates": [
          -0.13765298561954717,
          51.50639677837741
        ]
      },
      "properties": {
        "id": "SW1A1HJ",
        "quality": 10,
        "easting": 529235,
        "northing": 180305,
        "country": "E92000001",
        "nhsRegionalHealthAuthority": "E19000003",
        "nhsHealthAuthority": "E18000007",
        "county": "",
        "district": "E09000033",
        "ward": "E05000644"
      }
    },
    {
      "type": "Feature",
      "geometry": {
        "type": "Point",
        "coordinates": [
          -0.13741578581266092,
          51.504792156495654
        ]
      },
      "properties": {
        "id": "SW1A1HL",
        "quality": 10,
        "easting": 529256,
        "northing": 180127,
        "country": "E92000001",
        "nhsRegionalHealthAuthority": "E19000003",
        "nhsHealthAuthority": "E18000007",
        "county": "",
        "district": "E09000033",
        "ward": "E05000644"
      }
    },
    {
      "type": "Feature",
      "geometry": {
        "type": "Point",
        "coordinates": [
          -0.13741578581266092,
          51.504792156495654
        ]
      },
      "properties": {
        "id": "SW1A1JB",
        "quality": 10,
        "easting": 529256,
        "northing": 180127,
        "country": "E92000001",
        "nhsRegionalHealthAuthority": "E19000003",
        "nhsHealthAuthority": "E18000007",
        "county": "",
        "district": "E09000033",
        "ward": "E05000644"
      }
    },
    {
      "type": "Feature",
      "geometry": {
        "type": "Point",
        "coordinates": [
          -0.13852882774065717,
          51.50718413111543
        ]
      },
      "properties": {
        "id": "SW1A1JD",
        "quality": 10,
        "easting": 529172,
        "northing": 180391,
        "country": "E92000001",
        "nhsRegionalHealthAuthority": "E19000003",
        "nhsHealthAuthority": "E18000007",
        "county": "",
        "district": "E09000033",
        "ward": "E05000644"
      }
    },
    {
      "type": "Feature",
      "geometry": {
        "type": "Point",
        "coordinates": [
          -0.13836662192833726,
          51.506920742868715
        ]
      },
      "properties": {
        "id": "SW1A1JF",
        "quality": 10,
        "easting": 529184,
        "northing": 180362,
        "country": "E92000001",
        "nhsRegionalHealthAuthority": "E19000003",
        "nhsHealthAuthority": "E18000007",
        "county": "",
        "district": "E09000033",
        "ward": "E05000644"
      }
    },
    {
      "type": "Feature",
      "geometry": {
        "type": "Point",
        "coordinates": [
          -0.13831242214626827,
          51.507189689272614
        ]
      },
      "properties": {
        "id": "SW1A1JG",
        "quality": 10,
        "easting": 529187,
        "northing": 180392,
        "country": "E92000001",
        "nhsRegionalHealthAuthority": "E19000003",
        "nhsHealthAuthority": "E18000007",
        "county": "",
        "district": "E09000033",
        "ward": "E05000644"
      }
    },
    {
      "type": "Feature",
      "geometry": {
        "type": "Point",
        "coordinates": [
          -0.13776073684448137,
          51.50375438140207
        ]
      },
      "properties": {
        "id": "SW1A1JR",
        "quality": 10,
        "easting": 529235,
        "northing": 180011,
        "country": "E92000001",
        "nhsRegionalHealthAuthority": "E19000003",
        "nhsHealthAuthority": "E18000007",
        "county": "",
        "district": "E09000033",
        "ward": "E05000644"
      }
    },
    {
      "type": "Feature",
      "geometry": {
        "type": "Point",
        "coordinates": [
          -0.13899996713501134,
          51.50693978928619
        ]
      },
      "properties": {
        "id": "SW1A1JT",
        "quality": 10,
        "easting": 529140,
        "northing": 180363,
        "country": "E92000001",
        "nhsRegionalHealthAuthority": "E19000003",
        "nhsHealthAuthority": "E18000007",
        "county": "",
        "district": "E09000033",
        "ward": "E05000644"
      }
    },
    {
      "type": "Feature",
      "geometry": {
        "type": "Point",
        "coordinates": [
          -0.13869545076645956,
          51.50627842620758
        ]
      },
      "properties": {
        "id": "SW1A1LD",
        "quality": 10,
        "easting": 529163,
        "northing": 180290,
        "country": "E92000001",
        "nhsRegionalHealthAuthority": "E19000003",
        "nhsHealthAuthority": "E18000007",
        "county": "",
        "district": "E09000033",
        "ward": "E05000644"
      }
    },
    {
      "type": "Feature",
      "geometry": {
        "type": "Point",
        "coordinates": [
          -0.1383807978639659,
          51.50621947004364
        ]
      },
      "properties": {
        "id": "SW1A1LE",
        "quality": 10,
        "easting": 529185,
        "northing": 180284,
        "country": "E92000001",
        "nhsRegionalHealthAuthority": "E19000003",
        "nhsHealthAuthority": "E18000007",
        "county": "",
        "district": "E09000033",
        "ward": "E05000644"
      }
    },
    {
      "type": "Feature",
      "geometry": {
        "type": "Point",
        "coordinates": [
          -0.13741578581266092,
          51.504792156495654
        ]
      },
      "properties": {
        "id": "SW1A1LF",
        "quality": 10,
        "easting": 529256,
        "northing": 180127,
        "country": "E92000001",
        "nhsRegionalHealthAuthority": "E19000003",
        "nhsHealthAuthority": "E18000007",
        "county": "",
        "district": "E09000033",
        "ward": "E05000644"
      }
    },
    {
      "type": "Feature",
      "geometry": {
        "type": "Point",
        "coordinates": [
          -0.13834491873482047,
          51.506039029183796
        ]
      },
      "properties": {
        "id": "SW1A1LN",
        "quality": 10,
        "easting": 529188,
        "northing": 180264,
        "country": "E92000001",
        "nhsRegionalHealthAuthority": "E19000003",
        "nhsHealthAuthority": "E18000007",
        "county": "",
        "district": "E09000033",
        "ward": "E05000644"
      }
    },
    {
      "type": "Feature",
      "geometry": {
        "type": "Point",
        "coordinates": [
          -0.1388293504314754,
          51.50582187977301
        ]
      },
      "properties": {
        "id": "SW1A1LP",
        "quality": 10,
        "easting": 529155,
        "northing": 180239,
        "country": "E92000001",
        "nhsRegionalHealthAuthority": "E19000003",
        "nhsHealthAuthority": "E18000007",
        "county": "",
        "district": "E09000033",
        "ward": "E05000644"
      }
    },
    {
      "type": "Feature",
      "geometry": {
        "type": "Point",
        "coordinates": [
          -0.13910372448546426,
          51.505808247062475
        ]
      },
      "properties": {
        "id": "SW1A1LR",
        "quality": 10,
        "easting": 529136,
        "northing": 180237,
        "country": "E92000001",
        "nhsRegionalHealthAuthority": "E19000003",
        "nhsHealthAuthority": "E18000007",
        "county": "",
        "district": "E09000033",
        "ward": "E05000644"
      }
    },
    {
      "type": "Feature",
      "geometry": {
        "type": "Point",
        "coordinates": [
          -0.1386944864646019,
          51.50559490011565
        ]
      },
      "properties": {
        "id": "SW1A1LS",
        "quality": 10,
        "easting": 529165,
        "northing": 180214,
        "country": "E92000001",
        "nhsRegionalHealthAuthority": "E19000003",
        "nhsHealthAuthority": "E18000007",
        "county": "",
        "district": "E09000033",
        "ward": "E05000644"
      }
    },
    {
      "type": "Feature",
      "geometry": {
        "type": "Point",
        "coordinates": [
          -0.13790467909535964,
          51.50587914868684
        ]
      },
      "properties": {
        "id": "SW1A1LY",
        "quality": 10,
        "easting": 529219,
        "northing": 180247,
        "country": "E92000001",
        "nhsRegionalHealthAuthority": "E19000003",
        "nhsHealthAuthority": "E18000007",
        "county": "",
        "district": "E09000033",
        "ward": "E05000644"
      }
    },
    {
      "type": "Feature",
      "geometry": {
        "type": "Point",
        "coordinates": [
          -0.13797375841203058,
          51.50595219411614
        ]
      },
      "properties": {
        "id": "SW1A1LZ",
        "quality": 10,
        "easting": 529214,
        "northing": 180255,
        "country": "E92000001",
        "nhsRegionalHealthAuthority": "E19000003",
        "nhsHealthAuthority": "E18000007",
        "county": "",
        "district": "E09000033",
        "ward": "E05000644"
      }
    },
    {
      "type": "Feature",
      "geometry": {
        "type": "Point",
        "coordinates": [
          -0.13764386568131398,
          51.50556023207569
        ]
      },
      "properties": {
        "id": "SW1A1NE",
        "quality": 10,
        "easting": 529238,
        "northing": 180212,
        "country": "E92000001",
        "nhsRegionalHealthAuthority": "E19000003",
        "nhsHealthAuthority": "E18000007",
        "county": "",
        "district": "E09000033",
        "ward": "E05000644"
      }
    },
    {
      "type": "Feature",
      "geometry": {
        "type": "Point",
        "coordinates": [
          -0.13769707594914393,
          51.50566899990679
        ]
      },
      "properties": {
        "id": "SW1A1NF",
        "quality": 10,
        "easting": 529234,
        "northing": 180224,
        "country": "E92000001",
        "nhsRegionalHealthAuthority": "E19000003",
        "nhsHealthAuthority": "E18000007",
        "county": "",
        "district": "E09000033",
        "ward": "E05000644"
      }
    },
    {
      "type": "Feature",
      "geometry": {
        "type": "Point",
        "coordinates": [
          -0.13920283527552585,
          51.50514429616494
        ]
      },
      "properties": {
        "id": "SW1A1NH",
        "quality": 10,
        "easting": 529131,
        "northing": 180163,
        "country": "E92000001",
        "nhsRegionalHealthAuthority": "E19000003",
        "nhsHealthAuthority": "E18000007",
        "county": "",
        "district": "E09000033",
        "ward": "E05000644"
      }
    },
    {
      "type": "Feature",
      "geometry": {
        "type": "Point",
        "coordinates": [
          -0.13877455557213383,
          51.505398312605394
        ]
      },
      "properties": {
        "id": "SW1A1NJ",
        "quality": 10,
        "easting": 529160,
        "northing": 180192,
        "country": "E92000001",
        "nhsRegionalHealthAuthority": "E19000003",
        "nhsHealthAuthority": "E18000007",
        "county": "",
        "district": "E09000033",
        "ward": "E05000644"
      }
    },
    {
      "type": "Feature",
      "geometry": {
        "type": "Point",
        "coordinates": [
          -0.13920258891882864,
          51.50550403478496
        ]
      },
      "properties": {
        "id": "SW1A1NN",
        "quality": 10,
        "easting": 529130,
        "northing": 180203,
        "country": "E92000001",
        "nhsRegionalHealthAuthority": "E19000003",
        "nhsHealthAuthority": "E18000007",
        "county": "",
        "district": "E09000033",
        "ward": "E05000644"
      }
    },
    {
      "type": "Feature",
      "geometry": {
        "type": "Point",
        "coordinates": [
          -0.13818736925931008,
          51.50530804920242
        ]
      },
      "properties": {
        "id": "SW1A1NP",
        "quality": 10,
        "easting": 529201,
        "northing": 180183,
        "country": "E92000001",
        "nhsRegionalHealthAuthority": "E19000003",
        "nhsHealthAuthority": "E18000007",
        "county": "",
        "district": "E09000033",
        "ward": "E05000644"
      }
    },
    {
      "type": "Feature",
      "geometry": {
        "type": "Point",
        "coordinates": [
          -0.1383792447668984,
          51.504843430112416
        ]
      },
      "properties": {
        "id": "SW1A1NR",
        "quality": 10,
        "easting": 529189,
        "northing": 180131,
        "country": "E92000001",
        "nhsRegionalHealthAuthority": "E19000003",
        "nhsHealthAuthority": "E18000007",
        "county": "",
        "district": "E09000033",
        "ward": "E05000644"
      }
    },
    {
      "type": "Feature",
      "geometry": {
        "type": "Point",
        "coordinates": [
          -0.13787298048122743,
          51.50488935321302
        ]
      },
      "properties": {
        "id": "SW1A1NS",
        "quality": 10,
        "easting": 529224,
        "northing": 180137,
        "country": "E92000001",
        "nhsRegionalHealthAuthority": "E19000003",
        "nhsHealthAuthority": "E18000007",
        "county": "",
        "district": "E09000033",
        "ward": "E05000644"
      }
    },
    {
      "type": "Feature",
      "geometry": {
        "type": "Point",
        "coordinates": [
          -0.13856585151195472,
          51.50521512857786
        ]
      },
      "properties": {
        "id": "SW1A1NX",
        "quality": 10,
        "easting": 529175,
        "northing": 180172,
        "country": "E92000001",
        "nhsRegionalHealthAuthority": "E19000003",
        "nhsHealthAuthority": "E18000007",
        "county": "",
        "district": "E09000033",
        "ward": "E05000644"
      }
    },
    {
      "type": "Feature",
      "geometry": {
        "type": "Point",
        "coordinates": [
          -0.13808351240766442,
          51.50502759970665
        ]
      },
      "properties": {
        "id": "SW1A1NY",
        "quality": 10,
        "easting": 529209,
        "northing": 180152,
        "country": "E92000001",
        "nhsRegionalHealthAuthority": "E19000003",
        "nhsHealthAuthority": "E18000007",
        "county": "",
        "district": "E09000033",
        "ward": "E05000644"
      }
    },
    {
      "type": "Feature",
      "geometry": {
        "type": "Point",
        "coordinates": [
          -0.13728627436846777,
          51.505140848370594
        ]
      },
      "properties": {
        "id": "SW1A1PH",
        "quality": 10,
        "easting": 529264,
        "northing": 180166,
        "country": "E92000001",
        "nhsRegionalHealthAuthority": "E19000003",
        "nhsHealthAuthority": "E18000007",
        "county": "",
        "district": "E09000033",
        "ward": "E05000644"
      }
    },
    {
      "type": "Feature",
      "geometry": {
        "type": "Point",
        "coordinates": [
          -0.1375739470672555,
          51.50515441120227
        ]
      },
      "properties": {
        "id": "SW1A1PJ",
        "quality": 10,
        "easting": 529244,
        "northing": 180167,
        "country": "E92000001",
        "nhsRegionalHealthAuthority": "E19000003",
        "nhsHealthAuthority": "E18000007",
        "county": "",
        "district": "E09000033",
        "ward": "E05000644"
      }
    },
    {
      "type": "Feature",
      "geometry": {
        "type": "Point",
        "coordinates": [
          -0.13693382262255505,
          51.50459563523171
        ]
      },
      "properties": {
        "id": "SW1A1PL",
        "quality": 10,
        "easting": 529290,
        "northing": 180106,
        "country": "E92000001",
        "nhsRegionalHealthAuthority": "E19000003",
        "nhsHealthAuthority": "E18000007",
        "county": "",
        "district": "E09000033",
        "ward": "E05000644"
      }
    },
    {
      "type": "Feature",
      "geometry": {
        "type": "Point",
        "coordinates": [
          -0.1391967221983472,
          51.506709079019345
        ]
      },
      "properties": {
        "id": "SW1A1RA",
        "quality": 10,
        "easting": 529127,
        "northing": 180337,
        "country": "E92000001",
        "nhsRegionalHealthAuthority": "E19000003",
        "nhsHealthAuthority": "E18000007",
        "county": "",
        "district": "E09000033",
        "ward": "E05000644"
      }
    },
    {
      "type": "Feature",
      "geometry": {
        "type": "Point",
        "coordinates": [
          -0.13981859130712226,
          51.506655990437466
        ]
      },
      "properties": {
        "id": "SW1A1RB",
        "quality": 10,
        "easting": 529084,
        "northing": 180330,
        "country": "E92000001",
        "nhsRegionalHealthAuthority": "E19000003",
        "nhsHealthAuthority": "E18000007",
        "county": "",
        "district": "E09000033",
        "ward": "E05000644"
      }
    },
    {
      "type": "Feature",
      "geometry": {
        "type": "Point",
        "coordinates": [
          -0.13975121470319274,
          51.50618725644738
        ]
      },
      "properties": {
        "id": "SW1A1RD",
        "quality": 10,
        "easting": 529090,
        "northing": 180278,
        "country": "E92000001",
        "nhsRegionalHealthAuthority": "E19000003",
        "nhsHealthAuthority": "E18000007",
        "county": "",
        "district": "E09000033",
        "ward": "E05000644"
      }
    },
    {
      "type": "Feature",
      "geometry": {
        "type": "Point",
        "coordinates": [
          -0.1390279214603646,
          51.50660747114275
        ]
      },
      "properties": {
        "id": "SW1A1RE",
        "quality": 10,
        "easting": 529139,
        "northing": 180326,
        "country": "E92000001",
        "nhsRegionalHealthAuthority": "E19000003",
        "nhsHealthAuthority": "E18000007",
        "county": "",
        "district": "E09000033",
        "ward": "E05000644"
      }
    },
    {
      "type": "Feature",
      "geometry": {
        "type": "Point",
        "coordinates": [
          -0.1397122775673014,
          51.505727967106445
        ]
      },
      "properties": {
        "id": "SW1A1RG",
        "quality": 10,
        "easting": 529094,
        "northing": 180227,
        "country": "E92000001",
        "nhsRegionalHealthAuthority": "E19000003",
        "nhsHealthAuthority": "E18000007",
        "county": "",
        "district": "E09000033",
        "ward": "E05000644"
      }
    },
    {
      "type": "Feature",
      "geometry": {
        "type": "Point",
        "coordinates": [
          -0.1397122775673014,
          51.505727967106445
        ]
      },
      "properties": {
        "id": "SW1A1RJ",
        "quality": 10,
        "easting": 529094,
        "northing": 180227,
        "country": "E92000001",
        "nhsRegionalHealthAuthority": "E19000003",
        "nhsHealthAuthority": "E18000007",
        "county": "",
        "district": "E09000033",
        "ward": "E05000644"
      }
    },
    {
      "type": "Feature",
      "geometry": {
        "type": "Point",
        "coordinates": [
          -0.1397122775673014,
          51.505727967106445
        ]
      },
      "properties": {
        "id": "SW1A1RL",
        "quality": 10,
        "easting": 529094,
        "northing": 180227,
        "country": "E92000001",
        "nhsRegionalHealthAuthority": "E19000003",
        "nhsHealthAuthority": "E18000007",
        "county": "",
        "district": "E09000033",
        "ward": "E05000644"
      }
    },
    {
      "type": "Feature",
      "geometry": {
        "type": "Point",
        "coordinates": [
          -0.13975121470319274,
          51.50618725644738
        ]
      },
      "properties": {
        "id": "SW1A1RN",
        "quality": 10,
        "easting": 529090,
        "northing": 180278,
        "country": "E92000001",
        "nhsRegionalHealthAuthority": "E19000003",
        "nhsHealthAuthority": "E18000007",
        "county": "",
        "district": "E09000033",
        "ward": "E05000644"
      }
    },
    {
      "type": "Feature",
      "geometry": {
        "type": "Point",
        "coordinates": [
          -0.1390279214603646,
          51.50660747114275
        ]
      },
      "properties": {
        "id": "SW1A1RP",
        "quality": 10,
        "easting": 529139,
        "northing": 180326,
        "country": "E92000001",
        "nhsRegionalHealthAuthority": "E19000003",
        "nhsHealthAuthority": "E18000007",
        "county": "",
        "district": "E09000033",
        "ward": "E05000644"
      }
    },
    {
      "type": "Feature",
      "geometry": {
        "type": "Point",
        "coordinates": [
          -0.13419911997914444,
          51.48052129148481
        ]
      },
      "properties": {
        "id": "SW1A1WG",
        "quality": 10,
        "easting": 529548,
        "northing": 177434,
        "country": "E92000001",
        "nhsRegionalHealthAuthority": "E19000003",
        "nhsHealthAuthority": "E18000007",
        "county": "",
        "district": "E09000032",
        "ward": "E05000620"
      }
    },
    {
      "type": "Feature",
      "geometry": {
        "type": "Point",
        "coordinates": [
          -0.13419911997914444,
          51.48052129148481
        ]
      },
      "properties": {
        "id": "SW1A1WH",
        "quality": 10,
        "easting": 529548,
        "northing": 177434,
        "country": "E92000001",
        "nhsRegionalHealthAuthority": "E19000003",
        "nhsHealthAuthority": "E18000007",
        "county": "",
        "district": "E09000032",
        "ward": "E05000620"
      }
    },
    {
      "type": "Feature",
      "geometry": {
        "type": "Point",
        "coordinates": [
          -0.13419911997914444,
          51.48052129148481
        ]
      },
      "properties": {
        "id": "SW1A1WL",
        "quality": 10,
        "easting": 529548,
        "northing": 177434,
        "country": "E92000001",
        "nhsRegionalHealthAuthority": "E19000003",
        "nhsHealthAuthority": "E18000007",
        "county": "",
        "district": "E09000032",
        "ward": "E05000620"
      }
    },
    {
      "type": "Feature",
      "geometry": {
        "type": "Point",
        "coordinates": [
          -0.13419911997914444,
          51.48052129148481
        ]
      },
      "properties": {
        "id": "SW1A1WN",
        "quality": 10,
        "easting": 529548,
        "northing": 177434,
        "country": "E92000001",
        "nhsRegionalHealthAuthority": "E19000003",
        "nhsHealthAuthority": "E18000007",
        "county": "",
        "district": "E09000032",
        "ward": "E05000620"
      }
    },
    {
      "type": "Feature",
      "geometry": {
        "type": "Point",
        "coordinates": [
          -0.13419911997914444,
          51.48052129148481
        ]
      },
      "properties": {
        "id": "SW1A1WP",
        "quality": 10,
        "easting": 529548,
        "northing": 177434,
        "country": "E92000001",
        "nhsRegionalHealthAuthority": "E19000003",
        "nhsHealthAuthority": "E18000007",
        "county": "",
        "district": "E09000032",
        "ward": "E05000620"
      }
    },
    {
      "type": "Feature",
      "geometry": {
        "type": "Point",
        "coordinates": [
          -0.13419911997914444,
          51.48052129148481
        ]
      },
      "properties": {
        "id": "SW1A1WR",
        "quality": 10,
        "easting": 529548,
        "northing": 177434,
        "country": "E92000001",
        "nhsRegionalHealthAuthority": "E19000003",
        "nhsHealthAuthority": "E18000007",
        "county": "",
        "district": "E09000032",
        "ward": "E05000620"
      }
    },
    {
      "type": "Feature",
      "geometry": {
        "type": "Point",
        "coordinates": [
          -0.13419911997914444,
          51.48052129148481
        ]
      },
      "properties": {
        "id": "SW1A1WU",
        "quality": 10,
        "easting": 529548,
        "northing": 177434,
        "country": "E92000001",
        "nhsRegionalHealthAuthority": "E19000003",
        "nhsHealthAuthority": "E18000007",
        "county": "",
        "district": "E09000032",
        "ward": "E05000620"
      }
    },
    {
      "type": "Feature",
      "geometry": {
        "type": "Point",
        "coordinates": [
          -0.13419911997914444,
          51.48052129148481
        ]
      },
      "properties": {
        "id": "SW1A1WW",
        "quality": 10,
        "easting": 529548,
        "northing": 177434,
        "country": "E92000001",
        "nhsRegionalHealthAuthority": "E19000003",
        "nhsHealthAuthority": "E18000007",
        "county": "",
        "district": "E09000032",
        "ward": "E05000620"
      }
    },
    {
      "type": "Feature",
      "geometry": {
        "type": "Point",
        "coordinates": [
          -0.13419911997914444,
          51.48052129148481
        ]
      },
      "properties": {
        "id": "SW1A1WZ",
        "quality": 10,
        "easting": 529548,
        "northing": 177434,
        "country": "E92000001",
        "nhsRegionalHealthAuthority": "E19000003",
        "nhsHealthAuthority": "E18000007",
        "county": "",
        "district": "E09000032",
        "ward": "E05000620"
      }
    },
    {
      "type": "Feature",
      "geometry": {
        "type": "Point",
        "coordinates": [
          -0.13419911997914444,
          51.48052129148481
        ]
      },
      "properties": {
        "id": "SW1A1XB",
        "quality": 10,
        "easting": 529548,
        "northing": 177434,
        "country": "E92000001",
        "nhsRegionalHealthAuthority": "E19000003",
        "nhsHealthAuthority": "E18000007",
        "county": "",
        "district": "E09000032",
        "ward": "E05000620"
      }
    },
    {
      "type": "Feature",
      "geometry": {
        "type": "Point",
        "coordinates": [
          -0.13419911997914444,
          51.48052129148481
        ]
      },
      "properties": {
        "id": "SW1A1ZA",
        "quality": 10,
        "easting": 529548,
        "northing": 177434,
        "country": "E92000001",
        "nhsRegionalHealthAuthority": "E19000003",
        "nhsHealthAuthority": "E18000007",
        "county": "",
        "district": "E09000032",
        "ward": "E05000620"
      }
    },
    {
      "type": "Feature",
      "geometry": {
        "type": "Point",
        "coordinates": [
          -0.13419911997914444,
          51.48052129148481
        ]
      },
      "properties": {
        "id": "SW1A1ZB",
        "quality": 10,
        "easting": 529548,
        "northing": 177434,
        "country": "E92000001",
        "nhsRegionalHealthAuthority": "E19000003",
        "nhsHealthAuthority": "E18000007",
        "county": "",
        "district": "E09000032",
        "ward": "E05000620"
      }
    },
    {
      "type": "Feature",
      "geometry": {
        "type": "Point",
        "coordinates": [
          -0.1260888861686493,
          51.503028825393756
        ]
      },
      "properties": {
        "id": "SW1A2AA",
        "quality": 10,
        "easting": 530047,
        "northing": 179951,
        "country": "E92000001",
        "nhsRegionalHealthAuthority": "E19000003",
        "nhsHealthAuthority": "E18000007",
        "county": "",
        "district": "E09000033",
        "ward": "E05000644"
      }
    },
    {
      "type": "Feature",
      "geometry": {
        "type": "Point",
        "coordinates": [
          -0.1262676001860054,
          51.502887783916655
        ]
      },
      "properties": {
        "id": "SW1A2AB",
        "quality": 10,
        "easting": 530035,
        "northing": 179935,
        "country": "E92000001",
        "nhsRegionalHealthAuthority": "E19000003",
        "nhsHealthAuthority": "E18000007",
        "county": "",
        "district": "E09000033",
        "ward": "E05000644"
      }
    },
    {
      "type": "Feature",
      "geometry": {
        "type": "Point",
        "coordinates": [
          -0.12649875610484113,
          51.502873490192776
        ]
      },
      "properties": {
        "id": "SW1A2AD",
        "quality": 10,
        "easting": 530019,
        "northing": 179933,
        "country": "E92000001",
        "nhsRegionalHealthAuthority": "E19000003",
        "nhsHealthAuthority": "E18000007",
        "county": "",
        "district": "E09000033",
        "ward": "E05000644"
      }
    },
    {
      "type": "Feature",
      "geometry": {
        "type": "Point",
        "coordinates": [
          -0.12750189418095875,
          51.5012526814094
        ]
      },
      "properties": {
        "id": "SW1A2AE",
        "quality": 10,
        "easting": 529954,
        "northing": 179751,
        "country": "E92000001",
        "nhsRegionalHealthAuthority": "E19000003",
        "nhsHealthAuthority": "E18000007",
        "county": "",
        "district": "E09000033",
        "ward": "E05000644"
      }
    },
    {
      "type": "Feature",
      "geometry": {
        "type": "Point",
        "coordinates": [
          -0.12788850019878284,
          51.50518005490023
        ]
      },
      "properties": {
        "id": "SW1A2AF",
        "quality": 10,
        "easting": 529916,
        "northing": 180187,
        "country": "E92000001",
        "nhsRegionalHealthAuthority": "E19000003",
        "nhsHealthAuthority": "E18000007",
        "county": "",
        "district": "E09000033",
        "ward": "E05000644"
      }
    },
    {
      "type": "Feature",
      "geometry": {
        "type": "Point",
        "coordinates": [
          -0.12700016329728256,
          51.50224295591938
        ]
      },
      "properties": {
        "id": "SW1A2AG",
        "quality": 10,
        "easting": 529986,
        "northing": 179862,
        "country": "E92000001",
        "nhsRegionalHealthAuthority": "E19000003",
        "nhsHealthAuthority": "E18000007",
        "county": "",
        "district": "E09000033",
        "ward": "E05000644"
      }
    },
    {
      "type": "Feature",
      "geometry": {
        "type": "Point",
        "coordinates": [
          -0.12610433419485834,
          51.50194984240007
        ]
      },
      "properties": {
        "id": "SW1A2AH",
        "quality": 10,
        "easting": 530049,
        "northing": 179831,
        "country": "E92000001",
        "nhsRegionalHealthAuthority": "E19000003",
        "nhsHealthAuthority": "E18000007",
        "county": "",
        "district": "E09000033",
        "ward": "E05000644"
      }
    },
    {
      "type": "Feature",
      "geometry": {
        "type": "Point",
        "coordinates": [
          -0.125032433406279,
          51.50313784801683
        ]
      },
      "properties": {
        "id": "SW1A2AL",
        "quality": 10,
        "easting": 530120,
        "northing": 179965,
        "country": "E92000001",
        "nhsRegionalHealthAuthority": "E19000003",
        "nhsHealthAuthority": "E18000007",
        "county": "",
        "district": "E09000033",
        "ward": "E05000644"
      }
    },
    {
      "type": "Feature",
      "geometry": {
        "type": "Point",
        "coordinates": [
          -0.12518708055612557,
          51.501125757909065
        ]
      },
      "properties": {
        "id": "SW1A2AN",
        "quality": 10,
        "easting": 530115,
        "northing": 179741,
        "country": "E92000001",
        "nhsRegionalHealthAuthority": "E19000003",
        "nhsHealthAuthority": "E18000007",
        "county": "",
        "district": "E09000033",
        "ward": "E05000644"
      }
    },
    {
      "type": "Feature",
      "geometry": {
        "type": "Point",
        "coordinates": [
          -0.12750189418095875,
          51.5012526814094
        ]
      },
      "properties": {
        "id": "SW1A2AQ",
        "quality": 10,
        "easting": 529954,
        "northing": 179751,
        "country": "E92000001",
        "nhsRegionalHealthAuthority": "E19000003",
        "nhsHealthAuthority": "E18000007",
        "county": "",
        "district": "E09000033",
        "ward": "E05000644"
      }
    },
    {
      "type": "Feature",
      "geometry": {
        "type": "Point",
        "coordinates": [
          -0.125032433406279,
          51.50313784801683
        ]
      },
      "properties": {
        "id": "SW1A2AS",
        "quality": 10,
        "easting": 530120,
        "northing": 179965,
        "country": "E92000001",
        "nhsRegionalHealthAuthority": "E19000003",
        "nhsHealthAuthority": "E18000007",
        "county": "",
        "district": "E09000033",
        "ward": "E05000644"
      }
    },
    {
      "type": "Feature",
      "geometry": {
        "type": "Point",
        "coordinates": [
          -0.125032433406279,
          51.50313784801683
        ]
      },
      "properties": {
        "id": "SW1A2AT",
        "quality": 10,
        "easting": 530120,
        "northing": 179965,
        "country": "E92000001",
        "nhsRegionalHealthAuthority": "E19000003",
        "nhsHealthAuthority": "E18000007",
        "county": "",
        "district": "E09000033",
        "ward": "E05000644"
      }
    },
    {
      "type": "Feature",
      "geometry": {
        "type": "Point",
        "coordinates": [
          -0.12535555961993658,
          51.50369162272505
        ]
      },
      "properties": {
        "id": "SW1A2AU",
        "quality": 10,
        "easting": 530096,
        "northing": 180026,
        "country": "E92000001",
        "nhsRegionalHealthAuthority": "E19000003",
        "nhsHealthAuthority": "E18000007",
        "county": "",
        "district": "E09000033",
        "ward": "E05000644"
      }
    },
    {
      "type": "Feature",
      "geometry": {
        "type": "Point",
        "coordinates": [
          -0.12453176380769236,
          51.50550414694222
        ]
      },
      "properties": {
        "id": "SW1A2AW",
        "quality": 10,
        "easting": 530148,
        "northing": 180229,
        "country": "E92000001",
        "nhsRegionalHealthAuthority": "E19000003",
        "nhsHealthAuthority": "E18000007",
        "county": "",
        "district": "E09000033",
        "ward": "E05000644"
      }
    },
    {
      "type": "Feature",
      "geometry": {
        "type": "Point",
        "coordinates": [
          -0.12565507040324508,
          51.5044698584826
        ]
      },
      "properties": {
        "id": "SW1A2AX",
        "quality": 10,
        "easting": 530073,
        "northing": 180112,
        "country": "E92000001",
        "nhsRegionalHealthAuthority": "E19000003",
        "nhsHealthAuthority": "E18000007",
        "county": "",
        "district": "E09000033",
        "ward": "E05000644"
      }
    },
    {
      "type": "Feature",
      "geometry": {
        "type": "Point",
        "coordinates": [
          -0.12548042067885806,
          51.50486278424412
        ]
      },
      "properties": {
        "id": "SW1A2AY",
        "quality": 10,
        "easting": 530084,
        "northing": 180156,
        "country": "E92000001",
        "nhsRegionalHealthAuthority": "E19000003",
        "nhsHealthAuthority": "E18000007",
        "county": "",
        "district": "E09000033",
        "ward": "E05000644"
      }
    },
    {
      "type": "Feature",
      "geometry": {
        "type": "Point",
        "coordinates": [
          -0.12592582291255716,
          51.505949132812695
        ]
      },
      "properties": {
        "id": "SW1A2BA",
        "quality": 10,
        "easting": 530050,
        "northing": 180276,
        "country": "E92000001",
        "nhsRegionalHealthAuthority": "E19000003",
        "nhsHealthAuthority": "E18000007",
        "county": "",
        "district": "E09000033",
        "ward": "E05000644"
      }
    },
    {
      "type": "Feature",
      "geometry": {
        "type": "Point",
        "coordinates": [
          -0.12728965878535017,
          51.50678034298713
        ]
      },
      "properties": {
        "id": "SW1A2BB",
        "quality": 10,
        "easting": 529953,
        "northing": 180366,
        "country": "E92000001",
        "nhsRegionalHealthAuthority": "E19000003",
        "nhsHealthAuthority": "E18000007",
        "county": "",
        "district": "E09000033",
        "ward": "E05000644"
      }
    },
    {
      "type": "Feature",
      "geometry": {
        "type": "Point",
        "coordinates": [
          -0.12369940472955586,
          51.50576963257995
        ]
      },
      "properties": {
        "id": "SW1A2BD",
        "quality": 10,
        "easting": 530205,
        "northing": 180260,
        "country": "E92000001",
        "nhsRegionalHealthAuthority": "E19000003",
        "nhsHealthAuthority": "E18000007",
        "county": "",
        "district": "E09000033",
        "ward": "E05000644"
      }
    },
    {
      "type": "Feature",
      "geometry": {
        "type": "Point",
        "coordinates": [
          -0.12384083687416482,
          51.50513335126967
        ]
      },
      "properties": {
        "id": "SW1A2BE",
        "quality": 10,
        "easting": 530197,
        "northing": 180189,
        "country": "E92000001",
        "nhsRegionalHealthAuthority": "E19000003",
        "nhsHealthAuthority": "E18000007",
        "county": "",
        "district": "E09000033",
        "ward": "E05000644"
      }
    },
    {
      "type": "Feature",
      "geometry": {
        "type": "Point",
        "coordinates": [
          -0.1286027610366529,
          51.50252036338812
        ]
      },
      "properties": {
        "id": "SW1A2BJ",
        "quality": 10,
        "easting": 529874,
        "northing": 179890,
        "country": "E92000001",
        "nhsRegionalHealthAuthority": "E19000003",
        "nhsHealthAuthority": "E18000007",
        "county": "",
        "district": "E09000033",
        "ward": "E05000644"
      }
    },
    {
      "type": "Feature",
      "geometry": {
        "type": "Point",
        "coordinates": [
          -0.12788850019878284,
          51.50518005490023
        ]
      },
      "properties": {
        "id": "SW1A2BL",
        "quality": 10,
        "easting": 529916,
        "northing": 180187,
        "country": "E92000001",
        "nhsRegionalHealthAuthority": "E19000003",
        "nhsHealthAuthority": "E18000007",
        "county": "",
        "district": "E09000033",
        "ward": "E05000644"
      }
    },
    {
      "type": "Feature",
      "geometry": {
        "type": "Point",
        "coordinates": [
          -0.1281375237515162,
          51.50648809870208
        ]
      },
      "properties": {
        "id": "SW1A2BN",
        "quality": 10,
        "easting": 529895,
        "northing": 180332,
        "country": "E92000001",
        "nhsRegionalHealthAuthority": "E19000003",
        "nhsHealthAuthority": "E18000007",
        "county": "",
        "district": "E09000033",
        "ward": "E05000644"
      }
    },
    {
      "type": "Feature",
      "geometry": {
        "type": "Point",
        "coordinates": [
          -0.12518708055612557,
          51.501125757909065
        ]
      },
      "properties": {
        "id": "SW1A2BQ",
        "quality": 10,
        "easting": 530115,
        "northing": 179741,
        "country": "E92000001",
        "nhsRegionalHealthAuthority": "E19000003",
        "nhsHealthAuthority": "E18000007",
        "county": "",
        "district": "E09000033",
        "ward": "E05000644"
      }
    },
    {
      "type": "Feature",
      "geometry": {
        "type": "Point",
        "coordinates": [
          -0.12521273980146733,
          51.50611760597932
        ]
      },
      "properties": {
        "id": "SW1A2BS",
        "quality": 10,
        "easting": 530099,
        "northing": 180296,
        "country": "E92000001",
        "nhsRegionalHealthAuthority": "E19000003",
        "nhsHealthAuthority": "E18000007",
        "county": "",
        "district": "E09000033",
        "ward": "E05000644"
      }
    },
    {
      "type": "Feature",
      "geometry": {
        "type": "Point",
        "coordinates": [
          -0.12626075938534914,
          51.50586454939152
        ]
      },
      "properties": {
        "id": "SW1A2BU",
        "quality": 10,
        "easting": 530027,
        "northing": 180266,
        "country": "E92000001",
        "nhsRegionalHealthAuthority": "E19000003",
        "nhsHealthAuthority": "E18000007",
        "county": "",
        "district": "E09000033",
        "ward": "E05000644"
      }
    },
    {
      "type": "Feature",
      "geometry": {
        "type": "Point",
        "coordinates": [
          -0.1252116206212552,
          51.50579381926188
        ]
      },
      "properties": {
        "id": "SW1A2BX",
        "quality": 10,
        "easting": 530100,
        "northing": 180260,
        "country": "E92000001",
        "nhsRegionalHealthAuthority": "E19000003",
        "nhsHealthAuthority": "E18000007",
        "county": "",
        "district": "E09000033",
        "ward": "E05000644"
      }
    },
    {
      "type": "Feature",
      "geometry": {
        "type": "Point",
        "coordinates": [
          -0.1252788345324371,
          51.505911810362186
        ]
      },
      "properties": {
        "id": "SW1A2BY",
        "quality": 10,
        "easting": 530095,
        "northing": 180273,
        "country": "E92000001",
        "nhsRegionalHealthAuthority": "E19000003",
        "nhsHealthAuthority": "E18000007",
        "county": "",
        "district": "E09000033",
        "ward": "E05000644"
      }
    },
    {
      "type": "Feature",
      "geometry": {
        "type": "Point",
        "coordinates": [
          -0.13419911997914444,
          51.48052129148481
        ]
      },
      "properties": {
        "id": "SW1A2BZ",
        "quality": 10,
        "easting": 529548,
        "northing": 177434,
        "country": "E92000001",
        "nhsRegionalHealthAuthority": "E19000003",
        "nhsHealthAuthority": "E18000007",
        "county": "",
        "district": "E09000032",
        "ward": "E05000620"
      }
    },
    {
      "type": "Feature",
      "geometry": {
        "type": "Point",
        "coordinates": [
          -0.12502884351643556,
          51.506384473105484
        ]
      },
      "properties": {
        "id": "SW1A2DB",
        "quality": 10,
        "easting": 530111,
        "northing": 180326,
        "country": "E92000001",
        "nhsRegionalHealthAuthority": "E19000003",
        "nhsHealthAuthority": "E18000007",
        "county": "",
        "district": "E09000033",
        "ward": "E05000644"
      }
    },
    {
      "type": "Feature",
      "geometry": {
        "type": "Point",
        "coordinates": [
          -0.12554252882104658,
          51.50650960191654
        ]
      },
      "properties": {
        "id": "SW1A2DD",
        "quality": 10,
        "easting": 530075,
        "northing": 180339,
        "country": "E92000001",
        "nhsRegionalHealthAuthority": "E19000003",
        "nhsHealthAuthority": "E18000007",
        "county": "",
        "district": "E09000033",
        "ward": "E05000644"
      }
    },
    {
      "type": "Feature",
      "geometry": {
        "type": "Point",
        "coordinates": [
          -0.12409633183108948,
          51.501369127324836
        ]
      },
      "properties": {
        "id": "SW1A2DG",
        "quality": 10,
        "easting": 530190,
        "northing": 179770,
        "country": "E92000001",
        "nhsRegionalHealthAuthority": "E19000003",
        "nhsHealthAuthority": "E18000007",
        "county": "",
        "district": "E09000033",
        "ward": "E05000644"
      }
    },
    {
      "type": "Feature",
      "geometry": {
        "type": "Point",
        "coordinates": [
          -0.12518708055612557,
          51.501125757909065
        ]
      },
      "properties": {
        "id": "SW1A2DL",
        "quality": 10,
        "easting": 530115,
        "northing": 179741,
        "country": "E92000001",
        "nhsRegionalHealthAuthority": "E19000003",
        "nhsHealthAuthority": "E18000007",
        "county": "",
        "district": "E09000033",
        "ward": "E05000644"
      }
    },
    {
      "type": "Feature",
      "geometry": {
        "type": "Point",
        "coordinates": [
          -0.12539149596996002,
          51.506678065555185
        ]
      },
      "properties": {
        "id": "SW1A2DR",
        "quality": 10,
        "easting": 530085,
        "northing": 180358,
        "country": "E92000001",
        "nhsRegionalHealthAuthority": "E19000003",
        "nhsHealthAuthority": "E18000007",
        "county": "",
        "district": "E09000033",
        "ward": "E05000644"
      }
    },
    {
      "type": "Feature",
      "geometry": {
        "type": "Point",
        "coordinates": [
          -0.12618176176785695,
          51.50638491455111
        ]
      },
      "properties": {
        "id": "SW1A2DX",
        "quality": 10,
        "easting": 530031,
        "northing": 180324,
        "country": "E92000001",
        "nhsRegionalHealthAuthority": "E19000003",
        "nhsHealthAuthority": "E18000007",
        "county": "",
        "district": "E09000033",
        "ward": "E05000644"
      }
    },
    {
      "type": "Feature",
      "geometry": {
        "type": "Point",
        "coordinates": [
          -0.12592582291255716,
          51.505949132812695
        ]
      },
      "properties": {
        "id": "SW1A2DY",
        "quality": 10,
        "easting": 530050,
        "northing": 180276,
        "country": "E92000001",
        "nhsRegionalHealthAuthority": "E19000003",
        "nhsHealthAuthority": "E18000007",
        "county": "",
        "district": "E09000033",
        "ward": "E05000644"
      }
    },
    {
      "type": "Feature",
      "geometry": {
        "type": "Point",
        "coordinates": [
          -0.12257901726561826,
          51.50497825221306
        ]
      },
      "properties": {
        "id": "SW1A2EF",
        "quality": 10,
        "easting": 530285,
        "northing": 180174,
        "country": "E92000001",
        "nhsRegionalHealthAuthority": "E19000003",
        "nhsHealthAuthority": "E18000007",
        "county": "",
        "district": "E09000033",
        "ward": "E05000644"
      }
    },
    {
      "type": "Feature",
      "geometry": {
        "type": "Point",
        "coordinates": [
          -0.12593172416785736,
          51.50580532988054
        ]
      },
      "properties": {
        "id": "SW1A2EG",
        "quality": 10,
        "easting": 530050,
        "northing": 180260,
        "country": "E92000001",
        "nhsRegionalHealthAuthority": "E19000003",
        "nhsHealthAuthority": "E18000007",
        "county": "",
        "district": "E09000033",
        "ward": "E05000644"
      }
    },
    {
      "type": "Feature",
      "geometry": {
        "type": "Point",
        "coordinates": [
          -0.12257901726561826,
          51.50497825221306
        ]
      },
      "properties": {
        "id": "SW1A2EH",
        "quality": 10,
        "easting": 530285,
        "northing": 180174,
        "country": "E92000001",
        "nhsRegionalHealthAuthority": "E19000003",
        "nhsHealthAuthority": "E18000007",
        "county": "",
        "district": "E09000033",
        "ward": "E05000644"
      }
    },
    {
      "type": "Feature",
      "geometry": {
        "type": "Point",
        "coordinates": [
          -0.12257901726561826,
          51.50497825221306
        ]
      },
      "properties": {
        "id": "SW1A2EJ",
        "quality": 10,
        "easting": 530285,
        "northing": 180174,
        "country": "E92000001",
        "nhsRegionalHealthAuthority": "E19000003",
        "nhsHealthAuthority": "E18000007",
        "county": "",
        "district": "E09000033",
        "ward": "E05000644"
      }
    },
    {
      "type": "Feature",
      "geometry": {
        "type": "Point",
        "coordinates": [
          -0.12257901726561826,
          51.50497825221306
        ]
      },
      "properties": {
        "id": "SW1A2EL",
        "quality": 10,
        "easting": 530285,
        "northing": 180174,
        "country": "E92000001",
        "nhsRegionalHealthAuthority": "E19000003",
        "nhsHealthAuthority": "E18000007",
        "county": "",
        "district": "E09000033",
        "ward": "E05000644"
      }
    },
    {
      "type": "Feature",
      "geometry": {
        "type": "Point",
        "coordinates": [
          -0.12257901726561826,
          51.50497825221306
        ]
      },
      "properties": {
        "id": "SW1A2EP",
        "quality": 10,
        "easting": 530285,
        "northing": 180174,
        "country": "E92000001",
        "nhsRegionalHealthAuthority": "E19000003",
        "nhsHealthAuthority": "E18000007",
        "county": "",
        "district": "E09000033",
        "ward": "E05000644"
      }
    },
    {
      "type": "Feature",
      "geometry": {
        "type": "Point",
        "coordinates": [
          -0.12427840779964759,
          51.50360244890984
        ]
      },
      "properties": {
        "id": "SW1A2ER",
        "quality": 10,
        "easting": 530171,
        "northing": 180018,
        "country": "E92000001",
        "nhsRegionalHealthAuthority": "E19000003",
        "nhsHealthAuthority": "E18000007",
        "county": "",
        "district": "E09000033",
        "ward": "E05000644"
      }
    },
    {
      "type": "Feature",
      "geometry": {
        "type": "Point",
        "coordinates": [
          -0.12257901726561826,
          51.50497825221306
        ]
      },
      "properties": {
        "id": "SW1A2ES",
        "quality": 10,
        "easting": 530285,
        "northing": 180174,
        "country": "E92000001",
        "nhsRegionalHealthAuthority": "E19000003",
        "nhsHealthAuthority": "E18000007",
        "county": "",
        "district": "E09000033",
        "ward": "E05000644"
      }
    },
    {
      "type": "Feature",
      "geometry": {
        "type": "Point",
        "coordinates": [
          -0.12423963851825973,
          51.50384465548143
        ]
      },
      "properties": {
        "id": "SW1A2ET",
        "quality": 10,
        "easting": 530173,
        "northing": 180045,
        "country": "E92000001",
        "nhsRegionalHealthAuthority": "E19000003",
        "nhsHealthAuthority": "E18000007",
        "county": "",
        "district": "E09000033",
        "ward": "E05000644"
      }
    },
    {
      "type": "Feature",
      "geometry": {
        "type": "Point",
        "coordinates": [
          -0.12384083687416482,
          51.50513335126967
        ]
      },
      "properties": {
        "id": "SW1A2EU",
        "quality": 10,
        "easting": 530197,
        "northing": 180189,
        "country": "E92000001",
        "nhsRegionalHealthAuthority": "E19000003",
        "nhsHealthAuthority": "E18000007",
        "county": "",
        "district": "E09000033",
        "ward": "E05000644"
      }
    },
    {
      "type": "Feature",
      "geometry": {
        "type": "Point",
        "coordinates": [
          -0.12324261538783583,
          51.503909644815245
        ]
      },
      "properties": {
        "id": "SW1A2EX",
        "quality": 10,
        "easting": 530242,
        "northing": 180054,
        "country": "E92000001",
        "nhsRegionalHealthAuthority": "E19000003",
        "nhsHealthAuthority": "E18000007",
        "county": "",
        "district": "E09000033",
        "ward": "E05000644"
      }
    },
    {
      "type": "Feature",
      "geometry": {
        "type": "Point",
        "coordinates": [
          -0.12453176380769236,
          51.50550414694222
        ]
      },
      "properties": {
        "id": "SW1A2EY",
        "quality": 10,
        "easting": 530148,
        "northing": 180229,
        "country": "E92000001",
        "nhsRegionalHealthAuthority": "E19000003",
        "nhsHealthAuthority": "E18000007",
        "county": "",
        "district": "E09000033",
        "ward": "E05000644"
      }
    },
    {
      "type": "Feature",
      "geometry": {
        "type": "Point",
        "coordinates": [
          -0.13419911997914444,
          51.48052129148481
        ]
      },
      "properties": {
        "id": "SW1A2FF",
        "quality": 10,
        "easting": 529548,
        "northing": 177434,
        "country": "E92000001",
        "nhsRegionalHealthAuthority": "E19000003",
        "nhsHealthAuthority": "E18000007",
        "county": "",
        "district": "E09000032",
        "ward": "E05000620"
      }
    },
    {
      "type": "Feature",
      "geometry": {
        "type": "Point",
        "coordinates": [
          -0.12384083687416482,
          51.50513335126967
        ]
      },
      "properties": {
        "id": "SW1A2HB",
        "quality": 10,
        "easting": 530197,
        "northing": 180189,
        "country": "E92000001",
        "nhsRegionalHealthAuthority": "E19000003",
        "nhsHealthAuthority": "E18000007",
        "county": "",
        "district": "E09000033",
        "ward": "E05000644"
      }
    },
    {
      "type": "Feature",
      "geometry": {
        "type": "Point",
        "coordinates": [
          -0.12223926627504304,
          51.50553041433589
        ]
      },
      "properties": {
        "id": "SW1A2HD",
        "quality": 10,
        "easting": 530307,
        "northing": 180236,
        "country": "E92000001",
        "nhsRegionalHealthAuthority": "E19000003",
        "nhsHealthAuthority": "E18000007",
        "county": "",
        "district": "E09000033",
        "ward": "E05000644"
      }
    },
    {
      "type": "Feature",
      "geometry": {
        "type": "Point",
        "coordinates": [
          -0.12223926627504304,
          51.50553041433589
        ]
      },
      "properties": {
        "id": "SW1A2HE",
        "quality": 10,
        "easting": 530307,
        "northing": 180236,
        "country": "E92000001",
        "nhsRegionalHealthAuthority": "E19000003",
        "nhsHealthAuthority": "E18000007",
        "county": "",
        "district": "E09000033",
        "ward": "E05000644"
      }
    },
    {
      "type": "Feature",
      "geometry": {
        "type": "Point",
        "coordinates": [
          -0.12406167455039774,
          51.50607221670779
        ]
      },
      "properties": {
        "id": "SW1A2HJ",
        "quality": 10,
        "easting": 530179,
        "northing": 180293,
        "country": "E92000001",
        "nhsRegionalHealthAuthority": "E19000003",
        "nhsHealthAuthority": "E18000007",
        "county": "",
        "district": "E09000033",
        "ward": "E05000644"
      }
    },
    {
      "type": "Feature",
      "geometry": {
        "type": "Point",
        "coordinates": [
          -0.12475777550043629,
          51.505966434004485
        ]
      },
      "properties": {
        "id": "SW1A2HN",
        "quality": 10,
        "easting": 530131,
        "northing": 180280,
        "country": "E92000001",
        "nhsRegionalHealthAuthority": "E19000003",
        "nhsHealthAuthority": "E18000007",
        "county": "",
        "district": "E09000033",
        "ward": "E05000644"
      }
    },
    {
      "type": "Feature",
      "geometry": {
        "type": "Point",
        "coordinates": [
          -0.12515844010160715,
          51.50568504606748
        ]
      },
      "properties": {
        "id": "SW1A2HP",
        "quality": 10,
        "easting": 530104,
        "northing": 180248,
        "country": "E92000001",
        "nhsRegionalHealthAuthority": "E19000003",
        "nhsHealthAuthority": "E18000007",
        "county": "",
        "district": "E09000033",
        "ward": "E05000644"
      }
    },
    {
      "type": "Feature",
      "geometry": {
        "type": "Point",
        "coordinates": [
          -0.12750189418095875,
          51.5012526814094
        ]
      },
      "properties": {
        "id": "SW1A2HQ",
        "quality": 10,
        "easting": 529954,
        "northing": 179751,
        "country": "E92000001",
        "nhsRegionalHealthAuthority": "E19000003",
        "nhsHealthAuthority": "E18000007",
        "county": "",
        "district": "E09000033",
        "ward": "E05000644"
      }
    },
    {
      "type": "Feature",
      "geometry": {
        "type": "Point",
        "coordinates": [
          -0.12059783715634921,
          51.50514437500783
        ]
      },
      "properties": {
        "id": "SW1A2HR",
        "quality": 10,
        "easting": 530422,
        "northing": 180196,
        "country": "E92000001",
        "nhsRegionalHealthAuthority": "E19000003",
        "nhsHealthAuthority": "E18000007",
        "county": "",
        "district": "E09000033",
        "ward": "E05000644"
      }
    },
    {
      "type": "Feature",
      "geometry": {
        "type": "Point",
        "coordinates": [
          -0.12257901726561826,
          51.50497825221306
        ]
      },
      "properties": {
        "id": "SW1A2HU",
        "quality": 10,
        "easting": 530285,
        "northing": 180174,
        "country": "E92000001",
        "nhsRegionalHealthAuthority": "E19000003",
        "nhsHealthAuthority": "E18000007",
        "county": "",
        "district": "E09000033",
        "ward": "E05000644"
      }
    },
    {
      "type": "Feature",
      "geometry": {
        "type": "Point",
        "coordinates": [
          -0.12475777550043629,
          51.505966434004485
        ]
      },
      "properties": {
        "id": "SW1A2HW",
        "quality": 10,
        "easting": 530131,
        "northing": 180280,
        "country": "E92000001",
        "nhsRegionalHealthAuthority": "E19000003",
        "nhsHealthAuthority": "E18000007",
        "county": "",
        "district": "E09000033",
        "ward": "E05000644"
      }
    },
    {
      "type": "Feature",
      "geometry": {
        "type": "Point",
        "coordinates": [
          -0.12299302159362464,
          51.50121656773559
        ]
      },
      "properties": {
        "id": "SW1A2HZ",
        "quality": 10,
        "easting": 530267,
        "northing": 179755,
        "country": "E92000001",
        "nhsRegionalHealthAuthority": "E19000003",
        "nhsHealthAuthority": "E18000007",
        "county": "",
        "district": "E09000033",
        "ward": "E05000644"
      }
    },
    {
      "type": "Feature",
      "geometry": {
        "type": "Point",
        "coordinates": [
          -0.12273860120085976,
          51.5017970780636
        ]
      },
      "properties": {
        "id": "SW1A2JF",
        "quality": 10,
        "easting": 530283,
        "northing": 179820,
        "country": "E92000001",
        "nhsRegionalHealthAuthority": "E19000003",
        "nhsHealthAuthority": "E18000007",
        "county": "",
        "district": "E09000033",
        "ward": "E05000644"
      }
    },
    {
      "type": "Feature",
      "geometry": {
        "type": "Point",
        "coordinates": [
          -0.12165376615013093,
          51.50119512224693
        ]
      },
      "properties": {
        "id": "SW1A2JH",
        "quality": 10,
        "easting": 530360,
        "northing": 179755,
        "country": "E92000001",
        "nhsRegionalHealthAuthority": "E19000003",
        "nhsHealthAuthority": "E18000007",
        "county": "",
        "district": "E09000033",
        "ward": "E05000644"
      }
    },
    {
      "type": "Feature",
      "geometry": {
        "type": "Point",
        "coordinates": [
          -0.1241051908824812,
          51.50115342298205
        ]
      },
      "properties": {
        "id": "SW1A2JJ",
        "quality": 10,
        "easting": 530190,
        "northing": 179746,
        "country": "E92000001",
        "nhsRegionalHealthAuthority": "E19000003",
        "nhsHealthAuthority": "E18000007",
        "county": "",
        "district": "E09000033",
        "ward": "E05000644"
      }
    },
    {
      "type": "Feature",
      "geometry": {
        "type": "Point",
        "coordinates": [
          -0.12273231532413026,
          51.502300618284416
        ]
      },
      "properties": {
        "id": "SW1A2JL",
        "quality": 10,
        "easting": 530282,
        "northing": 179876,
        "country": "E92000001",
        "nhsRegionalHealthAuthority": "E19000003",
        "nhsHealthAuthority": "E18000007",
        "county": "",
        "district": "E09000033",
        "ward": "E05000644"
      }
    },
    {
      "type": "Feature",
      "geometry": {
        "type": "Point",
        "coordinates": [
          -0.12342688612718741,
          51.50117854398686
        ]
      },
      "properties": {
        "id": "SW1A2JN",
        "quality": 10,
        "easting": 530237,
        "northing": 179750,
        "country": "E92000001",
        "nhsRegionalHealthAuthority": "E19000003",
        "nhsHealthAuthority": "E18000007",
        "county": "",
        "district": "E09000033",
        "ward": "E05000644"
      }
    },
    {
      "type": "Feature",
      "geometry": {
        "type": "Point",
        "coordinates": [
          -0.12339550078700606,
          51.50089024691116
        ]
      },
      "properties": {
        "id": "SW1A2JR",
        "quality": 10,
        "easting": 530240,
        "northing": 179718,
        "country": "E92000001",
        "nhsRegionalHealthAuthority": "E19000003",
        "nhsHealthAuthority": "E18000007",
        "county": "",
        "district": "E09000033",
        "ward": "E05000644"
      }
    },
    {
      "type": "Feature",
      "geometry": {
        "type": "Point",
        "coordinates": [
          -0.12418161780252195,
          51.50069597270544
        ]
      },
      "properties": {
        "id": "SW1A2JX",
        "quality": 10,
        "easting": 530186,
        "northing": 179695,
        "country": "E92000001",
        "nhsRegionalHealthAuthority": "E19000003",
        "nhsHealthAuthority": "E18000007",
        "county": "",
        "district": "E09000033",
        "ward": "E05000644"
      }
    },
    {
      "type": "Feature",
      "geometry": {
        "type": "Point",
        "coordinates": [
          -0.12788850019878284,
          51.50518005490023
        ]
      },
      "properties": {
        "id": "SW1A2LG",
        "quality": 10,
        "easting": 529916,
        "northing": 180187,
        "country": "E92000001",
        "nhsRegionalHealthAuthority": "E19000003",
        "nhsHealthAuthority": "E18000007",
        "county": "",
        "district": "E09000033",
        "ward": "E05000644"
      }
    },
    {
      "type": "Feature",
      "geometry": {
        "type": "Point",
        "coordinates": [
          -0.12339550078700606,
          51.50089024691116
        ]
      },
      "properties": {
        "id": "SW1A2LW",
        "quality": 10,
        "easting": 530240,
        "northing": 179718,
        "country": "E92000001",
        "nhsRegionalHealthAuthority": "E19000003",
        "nhsHealthAuthority": "E18000007",
        "county": "",
        "district": "E09000033",
        "ward": "E05000644"
      }
    },
    {
      "type": "Feature",
      "geometry": {
        "type": "Point",
        "coordinates": [
          -0.12418051584507926,
          51.501073685714495
        ]
      },
      "properties": {
        "id": "SW1A2LZ",
        "quality": 10,
        "easting": 530185,
        "northing": 179737,
        "country": "E92000001",
        "nhsRegionalHealthAuthority": "E19000003",
        "nhsHealthAuthority": "E18000007",
        "county": "",
        "district": "E09000033",
        "ward": "E05000644"
      }
    },
    {
      "type": "Feature",
      "geometry": {
        "type": "Point",
        "coordinates": [
          -0.1241890053009549,
          51.50086696903246
        ]
      },
      "properties": {
        "id": "SW1A2NE",
        "quality": 10,
        "easting": 530185,
        "northing": 179714,
        "country": "E92000001",
        "nhsRegionalHealthAuthority": "E19000003",
        "nhsHealthAuthority": "E18000007",
        "county": "",
        "district": "E09000033",
        "ward": "E05000644"
      }
    },
    {
      "type": "Feature",
      "geometry": {
        "type": "Point",
        "coordinates": [
          -0.1241147976152163,
          51.501621243139596
        ]
      },
      "properties": {
        "id": "SW1A2NH",
        "quality": 10,
        "easting": 530188,
        "northing": 179798,
        "country": "E92000001",
        "nhsRegionalHealthAuthority": "E19000003",
        "nhsHealthAuthority": "E18000007",
        "county": "",
        "district": "E09000033",
        "ward": "E05000644"
      }
    },
    {
      "type": "Feature",
      "geometry": {
        "type": "Point",
        "coordinates": [
          -0.12371120928037814,
          51.50197452941491
        ]
      },
      "properties": {
        "id": "SW1A2NJ",
        "quality": 10,
        "easting": 530215,
        "northing": 179838,
        "country": "E92000001",
        "nhsRegionalHealthAuthority": "E19000003",
        "nhsHealthAuthority": "E18000007",
        "county": "",
        "district": "E09000033",
        "ward": "E05000644"
      }
    },
    {
      "type": "Feature",
      "geometry": {
        "type": "Point",
        "coordinates": [
          -0.12371120928037814,
          51.50197452941491
        ]
      },
      "properties": {
        "id": "SW1A2NL",
        "quality": 10,
        "easting": 530215,
        "northing": 179838,
        "country": "E92000001",
        "nhsRegionalHealthAuthority": "E19000003",
        "nhsHealthAuthority": "E18000007",
        "county": "",
        "district": "E09000033",
        "ward": "E05000644"
      }
    },
    {
      "type": "Feature",
      "geometry": {
        "type": "Point",
        "coordinates": [
          -0.12427840779964759,
          51.50360244890984
        ]
      },
      "properties": {
        "id": "SW1A2NP",
        "quality": 10,
        "easting": 530171,
        "northing": 180018,
        "country": "E92000001",
        "nhsRegionalHealthAuthority": "E19000003",
        "nhsHealthAuthority": "E18000007",
        "county": "",
        "district": "E09000033",
        "ward": "E05000644"
      }
    },
    {
      "type": "Feature",
      "geometry": {
        "type": "Point",
        "coordinates": [
          -0.12371120928037814,
          51.50197452941491
        ]
      },
      "properties": {
        "id": "SW1A2NS",
        "quality": 10,
        "easting": 530215,
        "northing": 179838,
        "country": "E92000001",
        "nhsRegionalHealthAuthority": "E19000003",
        "nhsHealthAuthority": "E18000007",
        "county": "",
        "district": "E09000033",
        "ward": "E05000644"
      }
    },
    {
      "type": "Feature",
      "geometry": {
        "type": "Point",
        "coordinates": [
          -0.1241890053009549,
          51.50086696903246
        ]
      },
      "properties": {
        "id": "SW1A2NU",
        "quality": 10,
        "easting": 530185,
        "northing": 179714,
        "country": "E92000001",
        "nhsRegionalHealthAuthority": "E19000003",
        "nhsHealthAuthority": "E18000007",
        "county": "",
        "district": "E09000033",
        "ward": "E05000644"
      }
    },
    {
      "type": "Feature",
      "geometry": {
        "type": "Point",
        "coordinates": [
          -0.12788850019878284,
          51.50518005490023
        ]
      },
      "properties": {
        "id": "SW1A2PA",
        "quality": 10,
        "easting": 529916,
        "northing": 180187,
        "country": "E92000001",
        "nhsRegionalHealthAuthority": "E19000003",
        "nhsHealthAuthority": "E18000007",
        "county": "",
        "district": "E09000033",
        "ward": "E05000644"
      }
    },
    {
      "type": "Feature",
      "geometry": {
        "type": "Point",
        "coordinates": [
          -0.12305617969681089,
          51.499328925072575
        ]
      },
      "properties": {
        "id": "SW1A2PW",
        "quality": 10,
        "easting": 530268,
        "northing": 179545,
        "country": "E92000001",
        "nhsRegionalHealthAuthority": "E19000003",
        "nhsHealthAuthority": "E18000007",
        "county": "",
        "district": "E09000033",
        "ward": "E05000644"
      }
    },
    {
      "type": "Feature",
      "geometry": {
        "type": "Point",
        "coordinates": [
          -0.12371120928037814,
          51.50197452941491
        ]
      },
      "properties": {
        "id": "SW1A2SH",
        "quality": 10,
        "easting": 530215,
        "northing": 179838,
        "country": "E92000001",
        "nhsRegionalHealthAuthority": "E19000003",
        "nhsHealthAuthority": "E18000007",
        "county": "",
        "district": "E09000033",
        "ward": "E05000644"
      }
    },
    {
      "type": "Feature",
      "geometry": {
        "type": "Point",
        "coordinates": [
          -0.12785098384487684,
          51.50679829951177
        ]
      },
      "properties": {
        "id": "SW1A2TS",
        "quality": 10,
        "easting": 529914,
        "northing": 180367,
        "country": "E92000001",
        "nhsRegionalHealthAuthority": "E19000003",
        "nhsHealthAuthority": "E18000007",
        "county": "",
        "district": "E09000033",
        "ward": "E05000644"
      }
    },
    {
      "type": "Feature",
      "geometry": {
        "type": "Point",
        "coordinates": [
          -0.12273860120085976,
          51.5017970780636
        ]
      },
      "properties": {
        "id": "SW1A2TT",
        "quality": 10,
        "easting": 530283,
        "northing": 179820,
        "country": "E92000001",
        "nhsRegionalHealthAuthority": "E19000003",
        "nhsHealthAuthority": "E18000007",
        "county": "",
        "district": "E09000033",
        "ward": "E05000644"
      }
    },
    {
      "type": "Feature",
      "geometry": {
        "type": "Point",
        "coordinates": [
          -0.13419911997914444,
          51.48052129148481
        ]
      },
      "properties": {
        "id": "SW1A2WA",
        "quality": 10,
        "easting": 529548,
        "northing": 177434,
        "country": "E92000001",
        "nhsRegionalHealthAuthority": "E19000003",
        "nhsHealthAuthority": "E18000007",
        "county": "",
        "district": "E09000032",
        "ward": "E05000620"
      }
    },
    {
      "type": "Feature",
      "geometry": {
        "type": "Point",
        "coordinates": [
          -0.12706730362043586,
          51.506228183681024
        ]
      },
      "properties": {
        "id": "SW1A2WH",
        "quality": 10,
        "easting": 529970,
        "northing": 180305,
        "country": "E92000001",
        "nhsRegionalHealthAuthority": "E19000003",
        "nhsHealthAuthority": "E18000007",
        "county": "",
        "district": "E09000033",
        "ward": "E05000644"
      }
    },
    {
      "type": "Feature",
      "geometry": {
        "type": "Point",
        "coordinates": [
          -0.13419911997914444,
          51.48052129148481
        ]
      },
      "properties": {
        "id": "SW1A2WZ",
        "quality": 10,
        "easting": 529548,
        "northing": 177434,
        "country": "E92000001",
        "nhsRegionalHealthAuthority": "E19000003",
        "nhsHealthAuthority": "E18000007",
        "county": "",
        "district": "E09000032",
        "ward": "E05000620"
      }
    },
    {
      "type": "Feature",
      "geometry": {
        "type": "Point",
        "coordinates": [
          -0.13419911997914444,
          51.48052129148481
        ]
      },
      "properties": {
        "id": "SW1A2ZF",
        "quality": 10,
        "easting": 529548,
        "northing": 177434,
        "country": "E92000001",
        "nhsRegionalHealthAuthority": "E19000003",
        "nhsHealthAuthority": "E18000007",
        "county": "",
        "district": "E09000032",
        "ward": "E05000620"
      }
    },
    {
      "type": "Feature",
      "geometry": {
        "type": "Point",
        "coordinates": [
          -0.13419911997914444,
          51.48052129148481
        ]
      },
      "properties": {
        "id": "SW1A2ZG",
        "quality": 10,
        "easting": 529548,
        "northing": 177434,
        "country": "E92000001",
        "nhsRegionalHealthAuthority": "E19000003",
        "nhsHealthAuthority": "E18000007",
        "county": "",
        "district": "E09000032",
        "ward": "E05000620"
      }
    },
    {
      "type": "Feature",
      "geometry": {
        "type": "Point",
        "coordinates": [
          -0.13419911997914444,
          51.48052129148481
        ]
      },
      "properties": {
        "id": "SW1A2ZH",
        "quality": 10,
        "easting": 529548,
        "northing": 177434,
        "country": "E92000001",
        "nhsRegionalHealthAuthority": "E19000003",
        "nhsHealthAuthority": "E18000007",
        "county": "",
        "district": "E09000032",
        "ward": "E05000620"
      }
    },
    {
      "type": "Feature",
      "geometry": {
        "type": "Point",
        "coordinates": [
          -0.13419911997914444,
          51.48052129148481
        ]
      },
      "properties": {
        "id": "SW1A2ZJ",
        "quality": 10,
        "easting": 529548,
        "northing": 177434,
        "country": "E92000001",
        "nhsRegionalHealthAuthority": "E19000003",
        "nhsHealthAuthority": "E18000007",
        "county": "",
        "district": "E09000032",
        "ward": "E05000620"
      }
    }
  ]
}